database_nexus-0.1.0.dist-info/licenses/LICENSE
nexus/__init__.py
nexus/backends/__init__.py
nexus/backends/base.py
nexus/backends/mongodb.py
nexus/backends/mysql.py
nexus/backends/postgresql.py
nexus/backends/redis.py
nexus/backends/sqlite.py
nexus/core/__init__.py
nexus/core/database.py
nexus/core/exceptions.py
nexus/core/field.py
nexus/core/model.py
nexus/core/query.py
nexus/migrations/__init__.py
nexus/migrations/engine.py
nexus/migrations/manager.py
nexus/migrations/migration.py
nexus/profiling/__init__.py
nexus/profiling/profiler.py
nexus/profiling/utils.py
nexus/utils/__init__.py
nexus/utils/types.py
nexus/utils/validators.py
database_nexus-0.1.0.dist-info/METADATA
database_nexus-0.1.0.dist-info/WHEEL
database_nexus-0.1.0.dist-info/top_level.txt
database_nexus-0.1.0.dist-info/RECORD
