Metadata-Version: 2.4
Name: database-nexus
Version: 0.1.0
Summary: Unified database framework for Python
Author-email: Your Name <your.email@example.com>
Project-URL: Homepage, https://github.com/yourusername/database-nexus
Project-URL: Repository, https://github.com/yourusername/database-nexus
Classifier: Development Status :: 3 - Alpha
Classifier: Intended Audience :: Developers
Classifier: License :: OSI Approved :: MIT License
Classifier: Programming Language :: Python :: 3
Classifier: Programming Language :: Python :: 3.8
Classifier: Programming Language :: Python :: 3.9
Classifier: Programming Language :: Python :: 3.10
Requires-Python: >=3.8
License-File: LICENSE
Requires-Dist: pydantic>=2.0.0
Requires-Dist: aiosqlite>=0.19.0
Requires-Dist: asyncpg>=0.27.0
Requires-Dist: typing-extensions>=4.0.0
Provides-Extra: mysql
Requires-Dist: aiomysql>=0.2.0; extra == "mysql"
Provides-Extra: mongodb
Requires-Dist: motor>=3.0.0; extra == "mongodb"
Provides-Extra: redis
Requires-Dist: redis>=4.5.0; extra == "redis"
Dynamic: license-file
